harlequin_mysql/__init__.py
harlequin_mysql/adapter.py
harlequin_mysql/catalog.py
harlequin_mysql/cli_options.py
harlequin_mysql/completions.py
harlequin_mysql/functions.tsv
harlequin_mysql/interactions.py
harlequin_mysql/keywords.csv
harlequin_mysql/py.typed
harlequin_mysql-1.2.0.dist-info/LICENSE
harlequin_mysql-1.2.0.dist-info/METADATA
harlequin_mysql-1.2.0.dist-info/WHEEL
harlequin_mysql-1.2.0.dist-info/entry_points.txt
harlequin_mysql-1.2.0.dist-info/RECORD
