Metadata-Version: 2.1
Name: harlequin-mysql
Version: 1.2.0
Summary: A Harlequin adapter for MySQL.
License: MIT
Author: Ted Conbeer
Author-email: tconbeer@users.noreply.github.com
Requires-Python: >=3.9,<3.14
Classifier: License :: OSI Approved :: MIT License
Classifier: Programming Language :: Python :: 3
Classifier: Programming Language :: Python :: 3.9
Classifier: Programming Language :: Python :: 3.10
Classifier: Programming Language :: Python :: 3.11
Requires-Dist: harlequin (>=1.25.0,<3)
Requires-Dist: mysql-connector-python (>=9.1.0,<10.0.0)
